Workbook

Sheet Treatment Profitability
A1: Treatment Profitability Analyzer
A2: Enter treatment price and direct costs — formulas calculate profit and margin automatically
A3: Rating System → | C3: ● 70%+ Excellent | E3: ● 50–69% Healthy | G3: ● Below 50% Needs Review
A5: Treatment | B5: Price ($) | C5: COGS ($) | D5: Supplies ($) | E5: Labor ($) | F5: Commission ($) | G5: Total Cost ($) | H5: Profit ($) | I5: Margin %
A6: ← Blue cells are inputs | Enter price and costs for each treatment | G6: ← Calculated automatically — do not edit
A7: Botox / Nuceiva | G7: =C7+D7+E7+F7 | H7: =IF(B7=0,"-",B7-(C7+D7+E7+F7)) | I7: =IF(B7=0,"-",(B7-(C7+D7+E7+F7))/B7)
A8: Dermal Filler | G8: =C8+D8+E8+F8 | H8: =IF(B8=0,"-",B8-(C8+D8+E8+F8)) | I8: =IF(B8=0,"-",(B8-(C8+D8+E8+F8))/B8)
A9: Sculptra | G9: =C9+D9+E9+F9 | H9: =IF(B9=0,"-",B9-(C9+D9+E9+F9)) | I9: =IF(B9=0,"-",(B9-(C9+D9+E9+F9))/B9)
A10: Morpheus8 Face | B10: 1000 | C10: 120 | D10: 10 | E10: 50 | F10: 100 | G10: =C10+D10+E10+F10 | H10: =IF(B10=0,"-",B10-(C10+D10+E10+F10)) | I10: =IF(B10=0,"-",(B10-(C10+D10+E10+F10))/B10)
A11: Morpheus8 Body | G11: =C11+D11+E11+F11 | H11: =IF(B11=0,"-",B11-(C11+D11+E11+F11)) | I11: =IF(B11=0,"-",(B11-(C11+D11+E11+F11))/B11)
A12: Lumecca (IPL) | G12: =C12+D12+E12+F12 | H12: =IF(B12=0,"-",B12-(C12+D12+E12+F12)) | I12: =IF(B12=0,"-",(B12-(C12+D12+E12+F12))/B12)
A13: Forma (RF) | G13: =C13+D13+E13+F13 | H13: =IF(B13=0,"-",B13-(C13+D13+E13+F13)) | I13: =IF(B13=0,"-",(B13-(C13+D13+E13+F13))/B13)
A14: Diolaze (Laser Hair) | G14: =C14+D14+E14+F14 | H14: =IF(B14=0,"-",B14-(C14+D14+E14+F14)) | I14: =IF(B14=0,"-",(B14-(C14+D14+E14+F14))/B14)
A15: HydraFacial | G15: =C15+D15+E15+F15 | H15: =IF(B15=0,"-",B15-(C15+D15+E15+F15)) | I15: =IF(B15=0,"-",(B15-(C15+D15+E15+F15))/B15)
A16: Chemical Peel | G16: =C16+D16+E16+F16 | H16: =IF(B16=0,"-",B16-(C16+D16+E16+F16)) | I16: =IF(B16=0,"-",(B16-(C16+D16+E16+F16))/B16)
A17: Microneedling | G17: =C17+D17+E17+F17 | H17: =IF(B17=0,"-",B17-(C17+D17+E17+F17)) | I17: =IF(B17=0,"-",(B17-(C17+D17+E17+F17))/B17)
A18: PRF Treatment | G18: =C18+D18+E18+F18 | H18: =IF(B18=0,"-",B18-(C18+D18+E18+F18)) | I18: =IF(B18=0,"-",(B18-(C18+D18+E18+F18))/B18)
A19: IV Therapy | G19: =C19+D19+E19+F19 | H19: =IF(B19=0,"-",B19-(C19+D19+E19+F19)) | I19: =IF(B19=0,"-",(B19-(C19+D19+E19+F19))/B19)
A20: Medical Weight Loss | G20: =C20+D20+E20+F20 | H20: =IF(B20=0,"-",B20-(C20+D20+E20+F20)) | I20: =IF(B20=0,"-",(B20-(C20+D20+E20+F20))/B20)
A21: Facial | G21: =C21+D21+E21+F21 | H21: =IF(B21=0,"-",B21-(C21+D21+E21+F21)) | I21: =IF(B21=0,"-",(B21-(C21+D21+E21+F21))/B21)
G22: =C22+D22+E22+F22 | H22: =IF(B22=0,"-",B22-(C22+D22+E22+F22)) | I22: =IF(B22=0,"-",(B22-(C22+D22+E22+F22))/B22)
G23: =C23+D23+E23+F23 | H23: =IF(B23=0,"-",B23-(C23+D23+E23+F23)) | I23: =IF(B23=0,"-",(B23-(C23+D23+E23+F23))/B23)
G24: =C24+D24+E24+F24 | H24: =IF(B24=0,"-",B24-(C24+D24+E24+F24)) | I24: =IF(B24=0,"-",(B24-(C24+D24+E24+F24))/B24)
G25: =C25+D25+E25+F25 | H25: =IF(B25=0,"-",B25-(C25+D25+E25+F25)) | I25: =IF(B25=0,"-",(B25-(C25+D25+E25+F25))/B25)
G26: =C26+D26+E26+F26 | H26: =IF(B26=0,"-",B26-(C26+D26+E26+F26)) | I26: =IF(B26=0,"-",(B26-(C26+D26+E26+F26))/B26)
A28: PORTFOLIO SUMMARY | G28: Portfolio Avg Margin: | H28: =IFERROR(AVERAGEIF(I7:I26,"<>-",I7:I26),"-")

Sheet Monthly Contribution
A1: Monthly Profit Contribution
A2: Enter monthly volume per treatment to see which services are driving the most profit
A3: Profit / Treatment pulls automatically from the Treatment Profitability tab — complete that tab first.
A5: Treatment | B5: Profit / Treatment ($) | C5: Monthly Volume | D5: Monthly Contribution ($) | E5: % of Total Profit
A6: ='Treatment Profitability'!A7 | B6: ='Treatment Profitability'!H7 | D6: =IF(OR(B6="-",C6="",C6=0),"-",B6*C6) | E6: =IF(OR(D6="-",SUMIF(D6:D25,"<>-",D6:D25)=0),"-",D6/SUMIF(D6:D25,"<>-",D6:D25))
A7: ='Treatment Profitability'!A8 | B7: ='Treatment Profitability'!H8 | D7: =IF(OR(B7="-",C7="",C7=0),"-",B7*C7) | E7: =IF(OR(D7="-",SUMIF(D6:D25,"<>-",D6:D25)=0),"-",D7/SUMIF(D6:D25,"<>-",D6:D25))
A8: ='Treatment Profitability'!A9 | B8: ='Treatment Profitability'!H9 | D8: =IF(OR(B8="-",C8="",C8=0),"-",B8*C8) | E8: =IF(OR(D8="-",SUMIF(D6:D25,"<>-",D6:D25)=0),"-",D8/SUMIF(D6:D25,"<>-",D6:D25))
A9: ='Treatment Profitability'!A10 | B9: ='Treatment Profitability'!H10 | D9: =IF(OR(B9="-",C9="",C9=0),"-",B9*C9) | E9: =IF(OR(D9="-",SUMIF(D6:D25,"<>-",D6:D25)=0),"-",D9/SUMIF(D6:D25,"<>-",D6:D25))
A10: ='Treatment Profitability'!A11 | B10: ='Treatment Profitability'!H11 | D10: =IF(OR(B10="-",C10="",C10=0),"-",B10*C10) | E10: =IF(OR(D10="-",SUMIF(D6:D25,"<>-",D6:D25)=0),"-",D10/SUMIF(D6:D25,"<>-",D6:D25))
A11: ='Treatment Profitability'!A12 | B11: ='Treatment Profitability'!H12 | D11: =IF(OR(B11="-",C11="",C11=0),"-",B11*C11) | E11: =IF(OR(D11="-",SUMIF(D6:D25,"<>-",D6:D25)=0),"-",D11/SUMIF(D6:D25,"<>-",D6:D25))
A12: ='Treatment Profitability'!A13 | B12: ='Treatment Profitability'!H13 | D12: =IF(OR(B12="-",C12="",C12=0),"-",B12*C12) | E12: =IF(OR(D12="-",SUMIF(D6:D25,"<>-",D6:D25)=0),"-",D12/SUMIF(D6:D25,"<>-",D6:D25))
A13: ='Treatment Profitability'!A14 | B13: ='Treatment Profitability'!H14 | D13: =IF(OR(B13="-",C13="",C13=0),"-",B13*C13) | E13: =IF(OR(D13="-",SUMIF(D6:D25,"<>-",D6:D25)=0),"-",D13/SUMIF(D6:D25,"<>-",D6:D25))
A14: ='Treatment Profitability'!A15 | B14: ='Treatment Profitability'!H15 | D14: =IF(OR(B14="-",C14="",C14=0),"-",B14*C14) | E14: =IF(OR(D14="-",SUMIF(D6:D25,"<>-",D6:D25)=0),"-",D14/SUMIF(D6:D25,"<>-",D6:D25))
A15: ='Treatment Profitability'!A16 | B15: ='Treatment Profitability'!H16 | D15: =IF(OR(B15="-",C15="",C15=0),"-",B15*C15) | E15: =IF(OR(D15="-",SUMIF(D6:D25,"<>-",D6:D25)=0),"-",D15/SUMIF(D6:D25,"<>-",D6:D25))
A16: ='Treatment Profitability'!A17 | B16: ='Treatment Profitability'!H17 | D16: =IF(OR(B16="-",C16="",C16=0),"-",B16*C16) | E16: =IF(OR(D16="-",SUMIF(D6:D25,"<>-",D6:D25)=0),"-",D16/SUMIF(D6:D25,"<>-",D6:D25))
A17: ='Treatment Profitability'!A18 | B17: ='Treatment Profitability'!H18 | D17: =IF(OR(B17="-",C17="",C17=0),"-",B17*C17) | E17: =IF(OR(D17="-",SUMIF(D6:D25,"<>-",D6:D25)=0),"-",D17/SUMIF(D6:D25,"<>-",D6:D25))
A18: ='Treatment Profitability'!A19 | B18: ='Treatment Profitability'!H19 | D18: =IF(OR(B18="-",C18="",C18=0),"-",B18*C18) | E18: =IF(OR(D18="-",SUMIF(D6:D25,"<>-",D6:D25)=0),"-",D18/SUMIF(D6:D25,"<>-",D6:D25))
A19: ='Treatment Profitability'!A20 | B19: ='Treatment Profitability'!H20 | D19: =IF(OR(B19="-",C19="",C19=0),"-",B19*C19) | E19: =IF(OR(D19="-",SUMIF(D6:D25,"<>-",D6:D25)=0),"-",D19/SUMIF(D6:D25,"<>-",D6:D25))
A20: ='Treatment Profitability'!A21 | B20: ='Treatment Profitability'!H21 | D20: =IF(OR(B20="-",C20="",C20=0),"-",B20*C20) | E20: =IF(OR(D20="-",SUMIF(D6:D25,"<>-",D6:D25)=0),"-",D20/SUMIF(D6:D25,"<>-",D6:D25))
A21: ='Treatment Profitability'!A22 | B21: ='Treatment Profitability'!H22 | D21: =IF(OR(B21="-",C21="",C21=0),"-",B21*C21) | E21: =IF(OR(D21="-",SUMIF(D6:D25,"<>-",D6:D25)=0),"-",D21/SUMIF(D6:D25,"<>-",D6:D25))
A22: ='Treatment Profitability'!A23 | B22: ='Treatment Profitability'!H23 | D22: =IF(OR(B22="-",C22="",C22=0),"-",B22*C22) | E22: =IF(OR(D22="-",SUMIF(D6:D25,"<>-",D6:D25)=0),"-",D22/SUMIF(D6:D25,"<>-",D6:D25))
A23: ='Treatment Profitability'!A24 | B23: ='Treatment Profitability'!H24 | D23: =IF(OR(B23="-",C23="",C23=0),"-",B23*C23) | E23: =IF(OR(D23="-",SUMIF(D6:D25,"<>-",D6:D25)=0),"-",D23/SUMIF(D6:D25,"<>-",D6:D25))
A24: ='Treatment Profitability'!A25 | B24: ='Treatment Profitability'!H25 | D24: =IF(OR(B24="-",C24="",C24=0),"-",B24*C24) | E24: =IF(OR(D24="-",SUMIF(D6:D25,"<>-",D6:D25)=0),"-",D24/SUMIF(D6:D25,"<>-",D6:D25))
A25: ='Treatment Profitability'!A26 | B25: ='Treatment Profitability'!H26 | D25: =IF(OR(B25="-",C25="",C25=0),"-",B25*C25) | E25: =IF(OR(D25="-",SUMIF(D6:D25,"<>-",D6:D25)=0),"-",D25/SUMIF(D6:D25,"<>-",D6:D25))
A26: TOTAL MONTHLY PROFIT | D26: =SUMIF(D6:D25,"<>-",D6:D25) | E26: 100%

Sheet How To Use
A1: How To Use This Spreadsheet
A3: STEP 1 — TREATMENT PROFITABILITY
A4: Treatment Name | B4: Enter the name of each treatment (e.g. Morpheus8 Face, Botox, HydraFacial).
A5: Price ($) | B5: What the patient pays. Blue cells = user input.
A6: COGS ($) | B6: Items directly consumed: injectables, device tips, PRF tubes, exosomes, cannulas.
A7: Supplies ($) | B7: Small consumables: gloves, gauze, alcohol pads, numbing cream, needles, syringes.
A8: Labor ($) | B8: Provider labor cost. Formula: Treatment Time (hrs) × Hourly Cost. Example: 60-min treatment, $50/hr cost = $50 labor.
A9: Commission ($) | B9: Percentage commission or flat-rate bonus paid to the provider. Example: 10% on $1,000 = $100.
A10: Total Cost | B10: Auto-calculated: COGS + Supplies + Labor + Commission.
A11: Profit | B11: Auto-calculated: Price − Total Cost.
A12: Margin % | B12: Auto-calculated: Profit ÷ Price. Color-coded automatically.
A14: PROFITABILITY RATING SYSTEM
A15: Green — 70%+ Margin | B15: Excellent. Prioritize marketing and volume for this treatment.
A16: Yellow — 50–69% Margin | B16: Healthy. Monitor costs and consider a modest price review.
A17: Red — Below 50% Margin | B17: Needs review. Evaluate pricing, costs, or whether to continue offering.
A19: STEP 2 — MONTHLY CONTRIBUTION
A20: Profit / Treatment | B20: Pulls automatically from the Profitability tab (green text = cross-sheet reference).
A21: Monthly Volume | B21: Enter how many times you perform this treatment per month. Blue = user input.
A22: Monthly Contribution | B22: Auto-calculated: Profit per Treatment × Monthly Volume.
A23: % of Total Profit | B23: Shows what percentage of your total monthly profit this treatment contributes.
A25: WHAT THIS HELPS YOU IDENTIFY
A26: High-margin treatments | B26: 70%+ margin = deserves more marketing, upsell focus, and priority scheduling.
A27: High-volume treatments | B27: High volume x lower margin can still be a major profit driver.
A28: Pricing opportunities | B28: Treatments below 50% margin may need a price increase or cost reduction.
A29: Portfolio balance | B29: Understand which treatments actually carry your practice vs. which are break-even.
A31: COLOR KEY
A32: Blue text | B32: User input — enter your data here.
A33: Black text | B33: Formula — calculated automatically. Do not edit.
A34: Green text | B34: Cross-sheet reference — pulled from another tab automatically.
